serverhub_agent
