Metadata-Version: 2.1
Name: serverhub-agent
Version: 0.0.22
Summary: Runtime interface to running docker containers
Home-page: https://github.yandex-team.ru/skills/serverhub-agent
License: UNKNOWN
Platform: UNKNOWN
Requires-Python: >=3.6
